{"results":[{"key":"3bok","value":"784980","msg":"1875"},{"key":"pupster","value":"783940","msg":"387"},{"key":"oknovaas","value":"783600","msg":0},{"key":"nemozoll","value":"782640","msg":"755"},{"key":"saintavgn","value":"764280","msg":"1453"},{"key":"entozhepasha","value":"759360","msg":"5104"},{"key":"lak0_n","value":"754680","msg":0},{"key":"0rangehorse","value":"751380","msg":"3688"},{"key":"hill_light","value":"750720","msg":"2132"},{"key":"d0lb1k_digital","value":"744840","msg":"7007"},{"key":"agufa","value":"744300","msg":"8192"},{"key":"thekphoenix","value":"738120","msg":0},{"key":"katranom","value":"734040","msg":"3260"},{"key":"dosvidariia","value":"733260","msg":"6332"},{"key":"shurpiee","value":"728700","msg":"11391"},{"key":"favorxo","value":"727080","msg":0},{"key":"kitsush1ro","value":"725880","msg":0},{"key":"anoki_i","value":"722040","msg":0},{"key":"rankage","value":"721680","msg":"1307"},{"key":"relanit","value":"718500","msg":"9363"},{"key":"1theskymint","value":"715020","msg":0},{"key":"langerman_fosp","value":"714360","msg":"1097"},{"key":"laakoon","value":"700380","msg":"439"},{"key":"1_arinakis_1","value":"693240","msg":"6403"},{"key":"gachucha","value":"689460","msg":"2869"},{"key":"cliemens","value":"687360","msg":0},{"key":"likimiko_qwq","value":"686280","msg":"1339"},{"key":"nessie_cherpak","value":"684960","msg":"256"},{"key":"p0teshno","value":"684900","msg":"6248"},{"key":"gurqk","value":"681480","msg":"919"},{"key":"uusakoo","value":"681120","msg":"4098"},{"key":"chipchilinka0_o","value":"676320","msg":"4896"},{"key":"bezonee","value":"675960","msg":0},{"key":"yourmistake18","value":"672720","msg":0},{"key":"tawmtawmz","value":"669120","msg":0},{"key":"diolkejiv","value":"668400","msg":0},{"key":"gaster4ik","value":"666840","msg":"4387"},{"key":"cheesorka","value":"663300","msg":"3358"},{"key":"kellopa","value":"662700","msg":"6220"},{"key":"peperannata","value":"661080","msg":"1862"},{"key":"kimigava","value":"654300","msg":"548"},{"key":"mishelllka","value":"653400","msg":"944"},{"key":"imac_coffee","value":"652680","msg":"17458"},{"key":"infnitelightness","value":"651540","msg":"150"},{"key":"grustnayk","value":"648360","msg":0},{"key":"evitta","value":"648060","msg":"215"},{"key":"feet","value":"646680","msg":"\":\"234"},{"key":"nropy","value":"645180","msg":"247"},{"key":"escalator_to_hell","value":"642840","msg":"8496"},{"key":"maikerusblv","value":"641520","msg":"3672"},{"key":"prishvin93","value":"638820","msg":"2896"},{"key":"stariy_telek","value":"637680","msg":0},{"key":"nikit_ohka","value":"636000","msg":"479"},{"key":"manmellon","value":"632460","msg":"5063"},{"key":"thiccur","value":"632340","msg":0},{"key":"meow_bark","value":"631380","msg":0},{"key":"f8cking8dreams","value":"631380","msg":0},{"key":"foutu","value":"627900","msg":0},{"key":"mayerkaa","value":"627300","msg":"913"},{"key":"lisitzinavgn","value":"627120","msg":"25473"},{"key":"oikawahoshi","value":"626940","msg":"4422"},{"key":"trostinochka","value":"625560","msg":"502"},{"key":"andrw1703","value":"625200","msg":"1262"},{"key":"etozhevanis","value":"622980","msg":0},{"key":"razvivatel","value":"620040","msg":"15981"},{"key":"norantonic","value":"619140","msg":0},{"key":"iwachaa","value":"618900","msg":"542"},{"key":"izzygayle","value":"615660","msg":0},{"key":"rrrrrrrrrregina","value":"613800","msg":"1356"},{"key":"anastacciaaa","value":"613380","msg":"7087"},{"key":"thekandk","value":"604620","msg":0},{"key":"tricky_rain","value":"603540","msg":0},{"key":"len1n__","value":"595140","msg":"2144"},{"key":"3lyuh","value":"589440","msg":"374"},{"key":"mimaky","value":"588060","msg":"569"},{"key":"tvoy_cringe","value":"586500","msg":0},{"key":"hocok_kocmohabta","value":"584940","msg":0},{"key":"isanotkisa","value":"581460","msg":"315"},{"key":"blue_church","value":"581100","msg":"175"},{"key":"dibennington","value":"580620","msg":"1061"},{"key":"viktorykay","value":"578580","msg":"1627"},{"key":"bloodynor","value":"577200","msg":"7409"},{"key":"xxrinakixx","value":"575400","msg":"2496"},{"key":"4uxpuk","value":"571740","msg":"1402"},{"key":"lalageyy","value":"571560","msg":"3415"},{"key":"pavukrobot","value":"568920","msg":0},{"key":"tsukkiny","value":"568920","msg":0},{"key":"panicbooooooooooooomb","value":"568800","msg":0},{"key":"katishka","value":"568140","msg":"380"},{"key":"redfeed_sa","value":"566580","msg":"2557"},{"key":"cleverm0nkey","value":"565920","msg":"198"},{"key":"muracles","value":"562560","msg":0},{"key":"mudak_posledniy","value":"561180","msg":"364"},{"key":"candytwix","value":"560760","msg":"1773"},{"key":"mdaliya","value":"559500","msg":"163"},{"key":"lemonlipmint","value":"559260","msg":0},{"key":"scp_euclid","value":"555780","msg":"281"},{"key":"night_driv3r","value":"554160","msg":0},{"key":"yasha2882","value":"550440","msg":"197"}]}