{"results":[{"key":"t2x2bot","value":"2569080","msg":0},{"key":"kotsumateya","value":"2300700","msg":"307"},{"key":"jockerpie","value":"1850040","msg":"1668"},{"key":"aroldas1","value":"1767900","msg":"1153"},{"key":"lumu_chan","value":"1764480","msg":0},{"key":"virgoproz","value":"1626180","msg":0},{"key":"ksenymio","value":"1616640","msg":0},{"key":"nisterol","value":"1571100","msg":0},{"key":"solnishka","value":"1566240","msg":0},{"key":"wijes","value":"1548420","msg":0},{"key":"v_and_k","value":"1464480","msg":0},{"key":"yeldorator","value":"1454880","msg":"2869"},{"key":"hochu_antoshu","value":"1431960","msg":"851"},{"key":"mallairr","value":"1393740","msg":"61713"},{"key":"rayadrawl","value":"1342980","msg":"5362"},{"key":"amedita","value":"1306746","msg":"224"},{"key":"etozhevoron","value":"1286100","msg":"9030"},{"key":"mezzanine1010","value":"1273560","msg":"175"},{"key":"endronist","value":"1258500","msg":"10805"},{"key":"rimastino","value":"1248060","msg":0},{"key":"shiro6willdietommorow9","value":"1238460","msg":"12092"},{"key":"shogeee","value":"1227120","msg":"18021"},{"key":"lizkapipiska101","value":"1180500","msg":"2972"},{"key":"alisych","value":"1174680","msg":"1154"},{"key":"igorpie","value":"1145460","msg":0},{"key":"sivuhas","value":"1142280","msg":"13575"},{"key":"kebabchic","value":"1128180","msg":"422"},{"key":"prostojulia_","value":"1115340","msg":"25602"},{"key":"ssuperfriend","value":"1087500","msg":"21875"},{"key":"grustnye_glaza","value":"1080480","msg":"20075"},{"key":"linnari","value":"1078380","msg":"618"},{"key":"bidlo2d","value":"1063740","msg":0},{"key":"ahrined2","value":"1062780","msg":0},{"key":"james72302","value":"1038840","msg":"14843"},{"key":"sylenthroll","value":"1019040","msg":0},{"key":"milkykitten123","value":"1011060","msg":"4776"},{"key":"nepriyatnost","value":"997500","msg":0},{"key":"wowsitb","value":"996420","msg":"2658"},{"key":"easynik","value":"967080","msg":"198"},{"key":"john_berberis","value":"952020","msg":"3846"},{"key":"kosadago","value":"951000","msg":"1766"},{"key":"drainpipe_flute","value":"948900","msg":"5930"},{"key":"itsvodoo","value":"948720","msg":0},{"key":"rudude351","value":"932640","msg":"2773"},{"key":"something_in_theway","value":"930480","msg":0},{"key":"lissabdya","value":"908520","msg":0},{"key":"achi_achi","value":"903420","msg":"4928"},{"key":"izzzyum","value":"893460","msg":"385"},{"key":"cute_blue_guy","value":"891660","msg":"279"},{"key":"taganffnafi","value":"885180","msg":"143"},{"key":"thesnowo","value":"877980","msg":"1192"},{"key":"hastur147","value":"868800","msg":0},{"key":"bilesst","value":"866340","msg":0},{"key":"kartoniumg","value":"859800","msg":"5735"},{"key":"shamiko","value":"859080","msg":"9422"},{"key":"fiku5golubev","value":"853740","msg":"16891"},{"key":"lauridge","value":"850080","msg":"311"},{"key":"conjurer61","value":"843420","msg":"1296"},{"key":"rozovoenebo","value":"832800","msg":"113"},{"key":"sheri_eze","value":"829440","msg":"7460"},{"key":"clopik_san","value":"826680","msg":"347"},{"key":"firestar6","value":"817200","msg":"1725"},{"key":"julieritterr","value":"811860","msg":"7901"},{"key":"htnv","value":"804120","msg":"1723"},{"key":"samomi","value":"802260","msg":0},{"key":"seth_rollins1337","value":"802080","msg":"475"},{"key":"safaetsoler","value":"799980","msg":"414"},{"key":"glebancki","value":"798480","msg":0},{"key":"nikita_sinai","value":"795000","msg":"6385"},{"key":"tunet5","value":"792720","msg":"9743"},{"key":"scd_monk","value":"786420","msg":"12043"},{"key":"kisyapolosataya","value":"785640","msg":"399"},{"key":"pupster","value":"783940","msg":"387"},{"key":"vorobushekl","value":"782880","msg":0},{"key":"ruvcheks","value":"771960","msg":"268"},{"key":"s_hirata_s","value":"771780","msg":0},{"key":"plaguemoon","value":"754800","msg":"2462"},{"key":"simultech","value":"748860","msg":"3430"},{"key":"nemnogoksusha","value":"743220","msg":"12125"},{"key":"nikkely","value":"741480","msg":"142"},{"key":"roach_8","value":"733620","msg":"1382"},{"key":"your_pirojok","value":"727320","msg":0},{"key":"agufa","value":"726420","msg":"7978"},{"key":"gorodche","value":"725760","msg":"1504"},{"key":"shinigami674","value":"724320","msg":"518"},{"key":"rankage","value":"721680","msg":"1307"},{"key":"entozhepasha","value":"714720","msg":"4863"},{"key":"langerman_fosp","value":"714360","msg":"1097"},{"key":"0rangehorse","value":"712380","msg":"3621"},{"key":"katranom","value":"709440","msg":"3255"},{"key":"dambboi","value":"698820","msg":0},{"key":"jave38","value":"694380","msg":"1535"},{"key":"sadchrk","value":"689880","msg":0},{"key":"kveevee","value":"687660","msg":"265"},{"key":"rozenps","value":"686880","msg":"3497"},{"key":"anoki_i","value":"685200","msg":0},{"key":"p0teshno","value":"684900","msg":"6248"},{"key":"nessie_cherpak","value":"684720","msg":"256"},{"key":"yourmistake18","value":"672720","msg":0},{"key":"chipchilinka0_o","value":"671280","msg":"4769"}]}