{"results":[{"key":"moskalbot","value":"2381820","msg":0},{"key":"kotsumateya","value":"2134020","msg":0},{"key":"jockerpie","value":"1692960","msg":"1598"},{"key":"aroldas1","value":"1636200","msg":"1020"},{"key":"lumu_chan","value":"1621860","msg":0},{"key":"ksenymio","value":"1608660","msg":0},{"key":"nisterol","value":"1452180","msg":0},{"key":"virgoproz","value":"1451940","msg":0},{"key":"solnishka","value":"1435380","msg":0},{"key":"wijes","value":"1370700","msg":0},{"key":"hochu_antoshu","value":"1362960","msg":"828"},{"key":"yeldorator","value":"1305060","msg":"2616"},{"key":"v_and_k","value":"1288800","msg":0},{"key":"rimastino","value":"1248060","msg":0},{"key":"mallairr","value":"1226700","msg":"50536"},{"key":"amedita","value":"1202526","msg":0},{"key":"rayadrawl","value":"1160100","msg":"5033"},{"key":"etozhevoron","value":"1136460","msg":"8632"},{"key":"mezzanine1010","value":"1132680","msg":0},{"key":"kebabchic","value":"1128180","msg":"422"},{"key":"shogeee","value":"1118760","msg":"16816"},{"key":"endronist","value":"1115760","msg":"8405"},{"key":"ssuperfriend","value":"1087500","msg":"21875"},{"key":"shiro6willdietommorow9","value":"1077660","msg":"10449"},{"key":"lizkapipiska101","value":"1062780","msg":"2499"},{"key":"sivuhas","value":"1052520","msg":"12757"},{"key":"james72302","value":"1035240","msg":"14843"},{"key":"alisych","value":"1026300","msg":"1031"},{"key":"igorpie","value":"991020","msg":0},{"key":"prostojulia_","value":"971940","msg":"20610"},{"key":"john_berberis","value":"945420","msg":"3846"},{"key":"bidlo2d","value":"933480","msg":0},{"key":"grustnye_glaza","value":"933360","msg":"16971"},{"key":"milkykitten123","value":"925860","msg":"4558"},{"key":"sylenthroll","value":"919740","msg":0},{"key":"easynik","value":"914760","msg":0},{"key":"linnari","value":"900360","msg":"411"},{"key":"ahrined2","value":"892620","msg":0},{"key":"itsvodoo","value":"887100","msg":0},{"key":"nepriyatnost","value":"881400","msg":0},{"key":"rudude351","value":"874920","msg":"2630"},{"key":"wowsitb","value":"860460","msg":"2051"},{"key":"shamiko","value":"859080","msg":"9422"},{"key":"kosadago","value":"852960","msg":"1486"},{"key":"something_in_theway","value":"836040","msg":0},{"key":"rozovoenebo","value":"812700","msg":0},{"key":"julieritterr","value":"811860","msg":"7901"},{"key":"drainpipe_flute","value":"804360","msg":"4046"},{"key":"lauridge","value":"786660","msg":0},{"key":"pupster","value":"783940","msg":"387"},{"key":"safaetsoler","value":"780600","msg":"413"},{"key":"achi_achi","value":"776760","msg":"4825"},{"key":"lissabdya","value":"761640","msg":0},{"key":"kartoniumg","value":"761280","msg":"5332"},{"key":"izzzyum","value":"753420","msg":0},{"key":"taganffnafi","value":"748020","msg":0},{"key":"scd_monk","value":"747960","msg":"11138"},{"key":"bilesst","value":"739560","msg":0},{"key":"firestar6","value":"735300","msg":"1444"},{"key":"cute_blue_guy","value":"734460","msg":0},{"key":"ruvcheks","value":"733620","msg":0},{"key":"hastur147","value":"733500","msg":0},{"key":"fiku5golubev","value":"732840","msg":"13213"},{"key":"sheri_eze","value":"729600","msg":"7396"},{"key":"rankage","value":"721680","msg":"1307"},{"key":"thesnowo","value":"719040","msg":"887"},{"key":"kisyapolosataya","value":"718080","msg":"392"},{"key":"langerman_fosp","value":"714360","msg":"1097"},{"key":"katranom","value":"709440","msg":"3255"},{"key":"samomi","value":"701580","msg":0},{"key":"glebancki","value":"697860","msg":0},{"key":"0rangehorse","value":"694620","msg":"3588"},{"key":"seth_rollins1337","value":"691140","msg":"397"},{"key":"conjurer61","value":"690240","msg":"959"},{"key":"chipchilinka0_o","value":"670860","msg":"4764"},{"key":"nikita_sinai","value":"666540","msg":"4271"},{"key":"your_pirojok","value":"664080","msg":0},{"key":"nessie_cherpak","value":"660300","msg":0},{"key":"tunet5","value":"659280","msg":"6350"},{"key":"nikkely","value":"652800","msg":0},{"key":"clopik_san","value":"648360","msg":0},{"key":"gorodche","value":"647820","msg":"1461"},{"key":"diolkejiv","value":"646980","msg":0},{"key":"anoki_i","value":"646080","msg":0},{"key":"htnv","value":"645360","msg":"1553"},{"key":"shinigami674","value":"637860","msg":"476"},{"key":"stariy_telek","value":"637680","msg":0},{"key":"nemnogoksusha","value":"636120","msg":"11083"},{"key":"s_hirata_s","value":"634980","msg":0},{"key":"agufa","value":"631260","msg":"6705"},{"key":"vorobushekl","value":"631020","msg":0},{"key":"rozenps","value":"629820","msg":"3272"},{"key":"p0teshno","value":"623160","msg":"5719"},{"key":"simultech","value":"623040","msg":"2003"},{"key":"plaguemoon","value":"621360","msg":"2300"},{"key":"thekandk","value":"604620","msg":0},{"key":"prishvin93","value":"603780","msg":"2316"},{"key":"entozhepasha","value":"598380","msg":"4105"},{"key":"yourmistake18","value":"591420","msg":0}]}